{
  "Traits": {
    "Name": "Grooxzan",
    "Race": "Land Squid",
    "Class": "Vermineer",
    "Level": 5
  },
  "dna": [
    0.47357441298663616,
    0.7538198898546398,
    0.01863071694970131,
    515039
  ],
  "seed": [
    0.4259076761081815,
    0.6455479848664254,
    0.2709055512677878,
    867704
  ],
  "birthday": "2022-12-08 16:00:03",
  "birthstamp": 1670486403.14029,
  "Stats": {
    "seed": [
      0.47357441298663616,
      0.7538198898546398,
      0.01863071694970131,
      515039
    ],
    "STR": 18,
    "best": "CON",
    "CON": 17,
    "DEX": 16,
    "INT": 11,
    "WIS": 14,
    "CHA": 10,
    "HP Max": 39,
    "MP Max": 24
  },
  "beststat": "CON 17",
  "task": "heading",
  "tasks": 4813,
  "elapsed": 17756,
  "bestequip": "+1 Canvas Cuisses",
  "Equips": {
    "Weapon": "Leafmace",
    "Shield": "+1 Fender",
    "Helm": "Rusty Leathers",
    "Hauberk": "+1 Macrame",
    "Brassairts": "+1 Canvas",
    "Vambraces": "-2 Chamois",
    "Gauntlets": "Flannel",
    "Gambeson": "-3 Torn Holey Scale Mail",
    "Cuisses": "+1 Canvas",
    "Greaves": "Flannel",
    "Sollerets": "-1 Chamois"
  },
  "Inventory": [
    [
      "Gold",
      146
    ]
  ],
  "Spells": [
    [
      "Hastiness",
      "II"
    ],
    [
      "Rabbit Punch",
      "II"
    ],
    [
      "Sadness",
      "I"
    ],
    [
      "Good Move",
      "I"
    ],
    [
      "Seasick",
      "II"
    ],
    [
      "Revolting Cloud",
      "I"
    ]
  ],
  "act": 1,
  "bestplot": "Act I",
  "Quests": [
    "Exterminate the Girl Scouts",
    "Fetch me an I.O.U.",
    "Exterminate the Beagles",
    "Fetch me a writ",
    "Deliver self canoe",
    "Deliver self rock",
    "Deliver self cookie",
    "Fetch me an egg",
    "Deliver self planter box",
    "Deliver self vest",
    "Fetch me a plank",
    "Placate the Porn Elementals",
    "Placate the Cockatrices",
    "Placate the Crayfishs",
    "Exterminate the Green Slimes",
    "Exterminate the Rats",
    "Placate the Vampires",
    "Exterminate the Octopuss",
    "Fetch me a sock",
    "Seek the Cruciate Gammel",
    "Placate the Su-monsters",
    "Seek the One True Sceptre",
    "Fetch me a trowel",
    "Placate the Harpys",
    "Exterminate the Medusas",
    "Deliver self credenza",
    "Placate the Owlbears",
    "Deliver self twig",
    "Placate the Gargoyles",
    "Seek the Blessed Ankh",
    "Fetch me a canoe",
    "Placate the Girl Scouts",
    "Fetch me a writ",
    "Exterminate the Leucrottas",
    "Placate the Dragon Turtles",
    "Seek the Filigreed Sceptre",
    "Placate the Xorns",
    "Placate the Eagle Scouts",
    "Fetch me a counterpane",
    "Seek the Legendary Corset",
    "Placate the Owlbears"
  ],
  "questmonster": "",
  "kill": "Heading to the killing fields...",
  "ExpBar": {
    "position": 2801.999999999998,
    "max": 6000,
    "percent": 46.0,
    "remaining": 3198,
    "time": "53.0 minutes",
    "hint": "3198 XP needed for next level"
  },
  "EncumBar": {
    "position": 0,
    "max": 28,
    "percent": 0,
    "remaining": 28,
    "time": "28 seconds",
    "hint": "0/28 cubits"
  },
  "PlotBar": {
    "position": 14831.999999999993,
    "max": 21600,
    "percent": 68.0,
    "remaining": 6768,
    "time": "112.0 minutes",
    "hint": "112.0 minutes remaining"
  },
  "QuestBar": {
    "position": 352.79999999999995,
    "max": 946,
    "percent": 37.0,
    "remaining": 593,
    "time": "9.0 minutes",
    "hint": "37% complete"
  },
  "TaskBar": {
    "position": 3252,
    "max": 4000,
    "percent": 81,
    "remaining": 748,
    "time": "12 minutes",
    "hint": "81%"
  },
  "queue": [],
  "date": "2022-12-08 16:00:03",
  "stamp": 1670486403.14029,
  "bestspell": "Seasick II",
  "questmonsterindex": 135,
  "bestquest": "Placate the Owlbears"
}